<?xml version="1.0" encoding="utf-8" ?><dwsync><file name="Joyce_Freeman,_B.S.,_CCHT.css" server="unix.ic.ucsc.edu/public_html/" local="3378223629" remote="16263125517" /><file name="Joyce_Freeman,_B.S.,_CCHT.js" server="unix.ic.ucsc.edu/public_html/" local="3378223629" remote="16263125517" /><file name="Joyce_Freeman,_B.S.,_CCHTIE.css" server="unix.ic.ucsc.edu/public_html/" local="3378223629" remote="16263125517" /><file name="Joyce_Freeman,_B.S.,_CCHTMoz.css" server="unix.ic.ucsc.edu/public_html/" local="3378223629" remote="16263125517" /><file name="mwmac.png" server="unix.ic.ucsc.edu/public_html/" local="3378223629" remote="16263125517" /><file name="NewTravel_C_BL.png" server="unix.ic.ucsc.edu/public_html/" local="3378223629" remote="16263125517" /><file name="NewTravel_C_BR.png" server="unix.ic.ucsc.edu/public_html/" local="3378223629" remote="16263125517" /><file name="NewTravel_C_TL.png" server="unix.ic.ucsc.edu/public_html/" local="3378223629" remote="16263125517" /><file name="NewTravel_C_TR.png" server="unix.ic.ucsc.edu/public_html/" local="3378223629" remote="16263125517" /><file name="NewTravel_S_B.png" server="unix.ic.ucsc.edu/public_html/" local="3378223629" remote="16263125517" /><file name="NewTravel_S_L.png" server="unix.ic.ucsc.edu/public_html/" local="3378223629" remote="16263125517" /><file name="NewTravel_S_R.png" server="unix.ic.ucsc.edu/public_html/" local="3378223629" remote="16263125517" /><file name="NewTravel_S_T.png" server="unix.ic.ucsc.edu/public_html/" local="3378223629" remote="16263125517" /><file name="Screen shot 2011-01-17 at 12.20.38 PM.jpg" server="unix.ic.ucsc.edu/public_html/" local="3378223628" remote="16263125516" /><file name="shapeimage_1.png" server="unix.ic.ucsc.edu/public_html/" local="3378223628" remote="16263125516" /><file name="shapeimage_2.png" server="unix.ic.ucsc.edu/public_html/" local="3378223628" remote="16263125516" /><file name="shapeimage_3.png" server="unix.ic.ucsc.edu/public_html/" local="3378223629" remote="16263125517" /></dwsync>